src/__init__.py
src/analysis/__init__.py
src/analysis/bleu_scores.py
src/analysis/visualize.py
src/data/__init__.py
src/data/caption_preprocessing.py
src/data/image_representations.py
src/data/load_data.py
src/data/make_dataset.py
src/data/split_and_format.py
src/models/LSTM_learner.py
src/models/__init__.py
src/models/decoder.py
src/models/predict.py
src/models/train.py
image_caption_generator_elizastarr-0.1.3.dist-info/LICENSE
image_caption_generator_elizastarr-0.1.3.dist-info/METADATA
image_caption_generator_elizastarr-0.1.3.dist-info/WHEEL
image_caption_generator_elizastarr-0.1.3.dist-info/top_level.txt
image_caption_generator_elizastarr-0.1.3.dist-info/RECORD
